objectref/__init__.py
objectref/py.typed
objectref-2023.10.31.dist-info/LICENSE
objectref-2023.10.31.dist-info/METADATA
objectref-2023.10.31.dist-info/WHEEL
objectref-2023.10.31.dist-info/top_level.txt
objectref-2023.10.31.dist-info/RECORD
