Metadata-Version: 2.1
Name: objectref
Version: 2023.10.31
Summary: deal with object reference notations
Author: Aaron Tsang
License: MIT
Project-URL: Homepage, https://github.com/tsangwpx/objectref
Project-URL: Source, https://github.com/tsangwpx/objectref
Classifier: Development Status :: 5 - Production/Stable
Classifier: License :: OSI Approved :: MIT License
Classifier: Operating System :: OS Independent
Classifier: Programming Language :: Python :: 3
Classifier: Programming Language :: Python :: 3.11
Classifier: Programming Language :: Python :: 3.10
Classifier: Programming Language :: Python :: 3.9
Classifier: Programming Language :: Python :: 3.8
Classifier: Programming Language :: Python :: 3.7
Classifier: Typing :: Typed
Requires-Python: >=3.7
License-File: LICENSE
Provides-Extra: dev
Requires-Dist: mypy >=1.5.1 ; extra == 'dev'
Requires-Dist: black >=23.9.0 ; extra == 'dev'
Requires-Dist: isort >=5.12.0 ; extra == 'dev'
Provides-Extra: test
Requires-Dist: pytest >=7.4.2 ; extra == 'test'
Requires-Dist: coverage[toml] >=6.4.4 ; extra == 'test'
